setup.py
stanley/__init__.py
stanley/config.py
stanley/content.py
stanley/filters.py
stanley/fs.py
stanley/jinjaext.py
stanley/main.py
stanley/parser.py
stanley/site.py
stanley/util.py
stanley.egg-info/PKG-INFO
stanley.egg-info/SOURCES.txt
stanley.egg-info/dependency_links.txt
stanley.egg-info/entry_points.txt
stanley.egg-info/not-zip-safe
stanley.egg-info/requires.txt
stanley.egg-info/top_level.txt
tests/__init__.py
tests/test_config.py
tests/test_content.py
tests/test_filters.py
tests/test_fs.py
tests/test_parser.py
tests/test_site.py